{
  "packages": {
    "image-set": {
      "displayName": "Example Items Template",
      "images": [
        {
          "filename": "hero1.webp",
          "label": "Super Handsome Blonde Hero",
          "tags": [
            "people",
            "hq"
          ]
        },
        {
          "filename": "hero2.webp",
          "label": "Handsome Hero",
          "tags": [
            "people",
            "1_0_0"
          ]
        },
        {
          "filename": "hero3.webp",
          "label": "hero3.webp",
          "tags": []
        },
        {
          "filename": "mecha/mecha1.webp",
          "label": "Flying Mecha",
          "tags": [
            "tech",
            "1_1_0"
          ]
        },
        {
          "filename": "mecha/mecha2.webp",
          "label": "mecha/mecha2.webp",
          "tags": []
        }
      ],
      "tags": {
        "people": {
          "title": "People",
          "description": "Images featuring individuals or groups of people",
          "category": "general"
        },
        "hq": {
          "title": "High Quality",
          "description": "Images with exceptional clarity and detail",
          "category": "general"
        },
        "1_0_0": {
          "title": "Image set Version 1",
          "description": "Images from Version 1",
          "category": "general"
        },
        "tech": {
          "title": "Technology",
          "description": "Images related to technological devices or concepts",
          "category": "general"
        },
        "1_1_0": {
          "title": "Image set Version 1.1",
          "description": "Images from Version 1.1",
          "category": "general"
        }
      }
    }
  }
}